{"cameraMode":{"drawMode":0,"name":"Shaded","section":"Shading Mode"},"sceneLighting":true,"audioPlay":false,"sceneViewState":{"showFog":true,"showMaterialUpdate":false,"showSkybox":true,"showFlares":true,"showImageEffects":true,"showParticleSystems":true},"in2DMode":false,"pivot":{"x":-2.0588207244873049,"y":32.776893615722659,"z":-1.9156243801116944},"rotation":{"x":0.4286060333251953,"y":-0.03928113356232643,"z":0.01865605264902115,"w":0.9024444222450256},"size":57.05609893798828,"orthographic":false}